{"GlobalPropertiesHash":"GS/px+4OKGWz59B43n0d+5tHnvqdn9nTioOOdD9l1NE=","FingerprintPatternsHash":"gq3WsqcKBUGTSNle7RKKyXRIwh7M8ccEqOqYvIzoM04=","PropertyOverridesHash":"8ZRc1sGeVrPBx4lD717BgRaQekyh78QKV9SKsdt638U=","InputHashes":["jDsELBI9k0H\u002Bac6A7n5I0yE2iigoB6/DHygEnR6yz6Y=","tkTYeumE4x7\u002BRytxmsCQWkrbw0/cxZhc/ZvQeQsMuC0=","ybui0SrOnj4JqL7FeRb7uurPpqDrwaVDSEZKLH/nieA=","tkFUvN6gUxLYP6VymUI5\u002BqxhKrfpErPFYRkGXXf5Q9s=","HLgdwRhFyr12Z3yWH5YRjrpzPiFqlHxKi9\u002BziqeXjuA=","WnR9i5lo6zyXrxmQ8NS/Z9bC5qHVn1QsY6NDJ5BkKUw=","BFL77nFZ7lkdDPJdHE5d6BtTbivSX5n26Mz1KDbJFc8=","DledL0wvHkyOwAXOhyA0pypB1R5XZpoam920YB4N\u002BeU=","rvXTBBoS0fcYdbG47wXsQy/NWWHwtjxD08ftXVP1gS8=","h05HRr9H\u002BMjyIMCQ65xRo\u002B3I6lyM2vbWSbhsK\u002BahZdg=","aNnq4xIPY\u002Bg7Fcvc7ZIin1tWzhKFM\u002BTerdGbJggiBe0=","Nx1kzvQxlNP87cDMViOJlcyfp5eDTLR85TFrZEvPP2g=","ZAKX0H7f4qCBg3ayohJLxmkA\u002Bj0zWZ1e7v2Txksu20o=","3NWCLC4C1/k/ivGJRYNXDKxIoJluCU2bv0BV0b1mIPE=","JeENdroIXnGfbv91Q8\u002BwfNlF\u002B0rpS0uPDk/532932mQ=","XAv7GcXfKPA1KjSyy5hswGd96WYh9KulDGFysp0yGZw=","JiPXPCMRS0LGE2L5FdDNpjN0bbYQcAJUwfQzK6Fla10=","oF3o1ahNG4zIwcCsncS1whwNyRgiGtSwijQLOTKTif8=","G/DvORnOiSiYAX05x\u002B2iQELSNQ6KWSWMt3CFf/ApQlM=","p6CkFF8Q5BSCDsgA7XQI6rHIZ0uN8qRmIzr16xeC8lo="],"CachedAssets":{"jDsELBI9k0H\u002Bac6A7n5I0yE2iigoB6/DHygEnR6yz6Y=":{"Identity":"C:\\Users\\eneso\\Source\\Repos\\allofthesestarshaveareason\\allofthesestarshaveareason\\wwwroot\\app.css","SourceId":"allofthesestarshaveareason","SourceType":"Discovered","ContentRoot":"C:\\Users\\eneso\\Source\\Repos\\allofthesestarshaveareason\\allofthesestarshaveareason\\wwwroot\\","BasePath":"_content/allofthesestarshaveareason","RelativePath":"app#[.{fingerprint}]?.css","AssetKind":"All","AssetMode":"All","AssetRole":"Primary","AssetMergeBehavior":null,"AssetMergeSource":"","RelatedAsset":null,"AssetTraitName":null,"AssetTraitValue":null,"Fingerprint":"da95v2qkru","Integrity":"u9qEka1auR7E3rd3/8/j8hkQdSOYj9bRJ4nYiFDR1sE=","CopyToOutputDirectory":"Never","CopyToPublishDirectory":"PreserveNewest","OriginalItemSpec":"wwwroot\\app.css","FileLength":2591,"LastWriteTime":"2025-10-20T15:59:14.6018559+00:00"},"tkTYeumE4x7\u002BRytxmsCQWkrbw0/cxZhc/ZvQeQsMuC0=":{"Identity":"C:\\Users\\eneso\\Source\\Repos\\allofthesestarshaveareason\\allofthesestarshaveareason\\wwwroot\\bootstrap\\bootstrap.min.css","SourceId":"allofthesestarshaveareason","SourceType":"Discovered","ContentRoot":"C:\\Users\\eneso\\Source\\Repos\\allofthesestarshaveareason\\allofthesestarshaveareason\\wwwroot\\","BasePath":"_content/allofthesestarshaveareason","RelativePath":"bootstrap/bootstrap.min#[.{fingerprint}]?.css","AssetKind":"All","AssetMode":"All","AssetRole":"Primary","AssetMergeBehavior":null,"AssetMergeSource":"","RelatedAsset":null,"AssetTraitName":null,"AssetTraitValue":null,"Fingerprint":"6gzpyzhau4","Integrity":"SiIVMGgRhdXjKSTIddX7mh9IbOXVcwQWc7/p4nS6D/0=","CopyToOutputDirectory":"Never","CopyToPublishDirectory":"PreserveNewest","OriginalItemSpec":"wwwroot\\bootstrap\\bootstrap.min.css","FileLength":162726,"LastWriteTime":"2025-10-20T15:59:14.6038637+00:00"},"ybui0SrOnj4JqL7FeRb7uurPpqDrwaVDSEZKLH/nieA=":{"Identity":"C:\\Users\\eneso\\Source\\Repos\\allofthesestarshaveareason\\allofthesestarshaveareason\\wwwroot\\bootstrap\\bootstrap.min.css.map","SourceId":"allofthesestarshaveareason","SourceType":"Discovered","ContentRoot":"C:\\Users\\eneso\\Source\\Repos\\allofthesestarshaveareason\\allofthesestarshaveareason\\wwwroot\\","BasePath":"_content/allofthesestarshaveareason","RelativePath":"bootstrap/bootstrap.min.css#[.{fingerprint}]?.map","AssetKind":"All","AssetMode":"All","AssetRole":"Primary","AssetMergeBehavior":null,"AssetMergeSource":"","RelatedAsset":null,"AssetTraitName":null,"AssetTraitValue":null,"Fingerprint":"8inm30yfxf","Integrity":"gBwg2tmA0Ci2u54gMF1jNCVku6vznarkLS6D76htNNQ=","CopyToOutputDirectory":"Never","CopyToPublishDirectory":"PreserveNewest","OriginalItemSpec":"wwwroot\\bootstrap\\bootstrap.min.css.map","FileLength":449111,"LastWriteTime":"2025-10-20T15:59:14.6053804+00:00"},"tkFUvN6gUxLYP6VymUI5\u002BqxhKrfpErPFYRkGXXf5Q9s=":{"Identity":"C:\\Users\\eneso\\Source\\Repos\\allofthesestarshaveareason\\allofthesestarshaveareason\\wwwroot\\favicon.png","SourceId":"allofthesestarshaveareason","SourceType":"Discovered","ContentRoot":"C:\\Users\\eneso\\Source\\Repos\\allofthesestarshaveareason\\allofthesestarshaveareason\\wwwroot\\","BasePath":"_content/allofthesestarshaveareason","RelativePath":"favicon#[.{fingerprint}]?.png","AssetKind":"All","AssetMode":"All","AssetRole":"Primary","AssetMergeBehavior":null,"AssetMergeSource":"","RelatedAsset":null,"AssetTraitName":null,"AssetTraitValue":null,"Fingerprint":"ifv42okdf2","Integrity":"4mWsDy3aHl36ZbGt8zByK7Pvd4kRUoNgTYzRnwmPHwg=","CopyToOutputDirectory":"Never","CopyToPublishDirectory":"PreserveNewest","OriginalItemSpec":"wwwroot\\favicon.png","FileLength":1148,"LastWriteTime":"2025-10-20T15:59:14.6066363+00:00"},"HLgdwRhFyr12Z3yWH5YRjrpzPiFqlHxKi9\u002BziqeXjuA=":{"Identity":"C:\\Users\\eneso\\Source\\Repos\\allofthesestarshaveareason\\allofthesestarshaveareason\\wwwroot\\ml-models\\model.onnx","SourceId":"allofthesestarshaveareason","SourceType":"Discovered","ContentRoot":"C:\\Users\\eneso\\Source\\Repos\\allofthesestarshaveareason\\allofthesestarshaveareason\\wwwroot\\","BasePath":"_content/allofthesestarshaveareason","RelativePath":"ml-models/model#[.{fingerprint}]?.onnx","AssetKind":"All","AssetMode":"All","AssetRole":"Primary","AssetMergeBehavior":null,"AssetMergeSource":"","RelatedAsset":null,"AssetTraitName":null,"AssetTraitValue":null,"Fingerprint":"hoy8hem7yi","Integrity":"b9XXL\u002BRYnxifjrwAZELbtSm7fOOPgIIRJoJSRhYEZFI=","CopyToOutputDirectory":"PreserveNewest","CopyToPublishDirectory":"PreserveNewest","OriginalItemSpec":"wwwroot\\ml-models\\model.onnx","FileLength":90405214,"LastWriteTime":"2025-10-20T18:41:54.2517194+00:00"},"WnR9i5lo6zyXrxmQ8NS/Z9bC5qHVn1QsY6NDJ5BkKUw=":{"Identity":"C:\\Users\\eneso\\Source\\Repos\\allofthesestarshaveareason\\allofthesestarshaveareason\\wwwroot\\ml-models\\vocab.txt","SourceId":"allofthesestarshaveareason","SourceType":"Discovered","ContentRoot":"C:\\Users\\eneso\\Source\\Repos\\allofthesestarshaveareason\\allofthesestarshaveareason\\wwwroot\\","BasePath":"_content/allofthesestarshaveareason","RelativePath":"ml-models/vocab#[.{fingerprint}]?.txt","AssetKind":"All","AssetMode":"All","AssetRole":"Primary","AssetMergeBehavior":null,"AssetMergeSource":"","RelatedAsset":null,"AssetTraitName":null,"AssetTraitValue":null,"Fingerprint":"3l5f6f4q7d","Integrity":"B\u002BztN1zsFE0nyQAkHz4zlHjeyVj5L928VR8pXJkgOKM=","CopyToOutputDirectory":"PreserveNewest","CopyToPublishDirectory":"PreserveNewest","OriginalItemSpec":"wwwroot\\ml-models\\vocab.txt","FileLength":231508,"LastWriteTime":"2025-10-20T19:34:40.8970658+00:00"}},"CachedCopyCandidates":{}}